increment/__init__.py
increment/_core.py
increment-1.3.5.dist-info/LICENSE
increment-1.3.5.dist-info/WHEEL
increment-1.3.5.dist-info/METADATA
increment-1.3.5.dist-info/RECORD
