Metadata-Version: 2.1
Name: increment
Version: 1.3.5
Summary: 分布式主键生成器，支持多机器|多进程|多线程并发生成
Keywords: increment
Author-email: "lcctoor.com" <lcctoor@outlook.com>
Requires-Python: >=3.7
Classifier: License :: OSI Approved :: Apache Software License
Project-URL: HomePage, https://lcctoor.github.io/lccpy/?package=increment
